README.md
setup.cfg
setup.py
cloudpost/__init__.py
cloudpost/__main__.py
cloudpost.egg-info/PKG-INFO
cloudpost.egg-info/SOURCES.txt
cloudpost.egg-info/dependency_links.txt
cloudpost.egg-info/entry_points.txt
cloudpost.egg-info/top_level.txt
cloudpost/_backends/gcp/__init__.py
cloudpost/_backends/gcp/_internal.py
cloudpost/_backends/gcp/_utils.py
cloudpost/_backends/gcp/bucket.py
cloudpost/_backends/gcp/container.py
cloudpost/_backends/gcp/exceptions.py
cloudpost/_backends/gcp/function.py
cloudpost/_backends/gcp/kvstore.py
cloudpost/_backends/gcp/queue.py
cloudpost/_backends/local/__init__.py
cloudpost/_backends/local/container.py
cloudpost/_backends/local/exceptions.py
cloudpost/_backends/local/kvstore.py
cloudpost/_backends/local/queue.py
cloudpost/_backends/local/storage.py
cloudpost/_deploy/gcp/__init__.py
cloudpost/_deploy/gcp/_gcloud.py
cloudpost/_deploy/gcp/_utils.py
cloudpost/_deploy/gcp/api.py
cloudpost/_deploy/gcp/bucket.py
cloudpost/_deploy/gcp/container.py
cloudpost/_deploy/gcp/function.py
cloudpost/_deploy/gcp/queue.py
cloudpost/_deploy/local/__init__.py
cloudpost/_deploy/local/_localRunner.py
cloudpost/_deploy/local/bucket.py
cloudpost/_deploy/local/function.py
cloudpost/_deploy/local/queue.py
cloudpost/cli/CloudProject.py
cloudpost/cli/DeployFactory.py
cloudpost/cli/FileAccess.py
cloudpost/cli/__init__.py
cloudpost/cli/__main__.py
cloudpost/cli/main.py
cloudpost/collector/__init__.py
cloudpost/depres/__init__.py