Metadata-Version: 2.1
Name: cloudpost
Version: 0.1.2
Summary: A tool which enables to construct your serverless infrastructure in Python code.
Home-page: https://github.com/lambda-lab/cloudpost
Author: Stefan Nozinic and Nikola Bebic
License: UNKNOWN
Download-URL: https://github.com/lambda-lab/cloudpost/tarball/0.1
Keywords: web,IaaC,cloud
Platform: UNKNOWN
